aiefftool/__init__.py
aiefftool/cli.py
aiefftool/read.py
aiefftool/git/__init__.py
aiefftool-0.1.0.dist-info/LICENSE
aiefftool-0.1.0.dist-info/METADATA
aiefftool-0.1.0.dist-info/WHEEL
aiefftool-0.1.0.dist-info/entry_points.txt
aiefftool-0.1.0.dist-info/top_level.txt
aiefftool-0.1.0.dist-info/RECORD
