Metadata-Version: 2.1
Name: aiefftool
Version: 0.1.0
Summary: ai effiency tool
Home-page: https://github.com/fengyunzaidushi/aiefftool
Author: fengyunzaidushi
Author-email: fengxiaoyang163@163.com
License: Apache Software License 2.0
Keywords: aiefftool
Requires-Python: >=3.10
License-File: LICENSE
Requires-Dist: chardet
